{
  "content": [
    {
      "userId": "LER47QJSFN2ZJQ06",
      "city": "",
      "about": "",
      "country": "",
      "nickname": "testUser1580246489",
      "username": "",
      "realName": "",
      "teamName": "",
      "avatarId": "bc7b1aee-9ad3-4f46-bdd2-04288e677ff5",
      "avatarSrc": "https://s3.fr-par.scw.cloud/dev-file-storage/bc7b1aee-9ad3-4f46-bdd2-04288e677ff5.png",
      "publicName": "testUser1580246489",
      "authStatus": "",
      "phoneNumber": "",
      "backgroundId": "",
      "backgroundSrc": "https://s3.fr-par.scw.cloud/dev-file-storage/62c8feaf-94ef-4675-b6ad-bb4e530fffa2.png",
      "stateProvince": "",
      "status": "OFFLINE",
      "lastVisit": "2023-04-26T18:56:57.832",
      "memberSince": "2023-04-04T08:20:12.435",
      "blockedMe": false,
      "friendRequestSent": true,
      "postsCount": 0,
      "friendsCount": 1,
      "followedCount": 0,
      "followersCount": 0,
      "blockedUsersCount": 0,
      "friendRequestsCount": 0,
      "avatarThumbId": [
        "bc7b1aee-9ad3-4f46-bdd2-04288e677ff5"
      ],
      "avatarThumbSrc": [
        "https://s3.fr-par.scw.cloud/dev-file-storage/bc7b1aee-9ad3-4f46-bdd2-04288e677ff5.png"
      ],
      "isFriend": true,
      "isFollowed": false,
      "isBlockedByMe": false
    },
    {
      "userId": "VAXQZ0V6FLTX8PMJ",
      "city": "Paris",
      "about": "I do the splits",
      "country": "AO",
      "nickname": "VanDamm",
      "username": "",
      "realName": "VanDamm",
      "teamName": "Bwanga",
      "avatarId": "VAXQZ0V6FLTX8PMJ/2023/4/f4fe6178-a802-40b8-a645-1798622221c0",
      "avatarSrc": "https://cdn.sandbox.inui.store/sandbox-media-storage/VAXQZ0V6FLTX8PMJ/2023/4/f4fe6178-a802-40b8-a645-1798622221c0.gif",
      "publicName": "VanDamm",
      "authStatus": "",
      "phoneNumber": "999999999999999999",
      "backgroundId": "ef533f33-58e8-4767-8a08-ae3401e4ad2e",
      "backgroundSrc": "https://s3.fr-par.scw.cloud/sandbox-media-storage/ef533f33-58e8-4767-8a08-ae3401e4ad2e.gif",
      "stateProvince": "France",
      "status": "OFFLINE",
      "lastVisit": "2023-04-17T11:38:20.184",
      "memberSince": "2023-03-24T06:47:56.576",
      "blockedMe": false,
      "friendRequestSent": true,
      "postsCount": 6,
      "friendsCount": 1,
      "followedCount": 0,
      "followersCount": 0,
      "blockedUsersCount": 0,
      "friendRequestsCount": 0,
      "avatarThumbId": [
        "VAXQZ0V6FLTX8PMJ/2023/4/f4fe6178-a802-40b8-a645-1798622221c0"
      ],
      "avatarThumbSrc": [
        "https://cdn.sandbox.inui.store/sandbox-media-storage/VAXQZ0V6FLTX8PMJ/2023/4/f4fe6178-a802-40b8-a645-1798622221c0.gif"
      ],
      "isFriend": true,
      "isFollowed": false,
      "isBlockedByMe": false
    },
    {
      "userId": "LER47QJSFN2ZJQ01",
      "city": "Paris",
      "about": "I do the splits",
      "country": "AO",
      "nickname": "Alezi",
      "username": "",
      "realName": "Alezi",
      "teamName": "France girls",
      "avatarId": "bc7b1aee-9ad3-4f46-bdd2-04288e677ff5",
      "avatarSrc": "https://s3.fr-par.scw.cloud/dev-file-storage/bc7b1aee-9ad3-4f46-bdd2-04288e677ff5.png",
      "publicName": "Alezi",
      "authStatus": "",
      "phoneNumber": "999999999999999999",
      "backgroundId": "",
      "backgroundSrc": "https://s3.fr-par.scw.cloud/dev-file-storage/62c8feaf-94ef-4675-b6ad-bb4e530fffa2.png",
      "stateProvince": "France",
      "status": "OFFLINE",
      "lastVisit": "2023-04-26T18:43:59.45",
      "memberSince": "2023-03-28T14:07:55.927",
      "blockedMe": false,
      "friendRequestSent": true,
      "postsCount": 0,
      "friendsCount": 1,
      "followedCount": 1,
      "followersCount": 0,
      "blockedUsersCount": 0,
      "friendRequestsCount": 0,
      "avatarThumbId": [
        "bc7b1aee-9ad3-4f46-bdd2-04288e677ff5"
      ],
      "avatarThumbSrc": [
        "https://s3.fr-par.scw.cloud/dev-file-storage/bc7b1aee-9ad3-4f46-bdd2-04288e677ff5.png"
      ],
      "isFriend": true,
      "isFollowed": true,
      "isBlockedByMe": false
    },
    {
      "userId": "LER47QJSFN2ZJQ05",
      "city": "",
      "about": "",
      "country": "",
      "nickname": "testUser-1929202870",
      "username": "",
      "realName": "",
      "teamName": "",
      "avatarId": "bc7b1aee-9ad3-4f46-bdd2-04288e677ff5",
      "avatarSrc": "https://s3.fr-par.scw.cloud/dev-file-storage/bc7b1aee-9ad3-4f46-bdd2-04288e677ff5.png",
      "publicName": "testUser-1929202870",
      "authStatus": "",
      "phoneNumber": "",
      "backgroundId": "",
      "backgroundSrc": "https://s3.fr-par.scw.cloud/dev-file-storage/62c8feaf-94ef-4675-b6ad-bb4e530fffa2.png",
      "stateProvince": "",
      "status": "OFFLINE",
      "lastVisit": "2023-04-26T18:57:09.596",
      "memberSince": "2023-04-04T08:20:08.897",
      "blockedMe": false,
      "friendRequestSent": true,
      "postsCount": 0,
      "friendsCount": 1,
      "followedCount": 0,
      "followersCount": 0,
      "blockedUsersCount": 0,
      "friendRequestsCount": 0,
      "avatarThumbId": [
        "bc7b1aee-9ad3-4f46-bdd2-04288e677ff5"
      ],
      "avatarThumbSrc": [
        "https://s3.fr-par.scw.cloud/dev-file-storage/bc7b1aee-9ad3-4f46-bdd2-04288e677ff5.png"
      ],
      "isFriend": true,
      "isFollowed": false,
      "isBlockedByMe": false
    }
  ],
  "number": 0,
  "size": 20,
  "totalPages": 1,
  "totalElements": 5,
  "empty": false,
  "first": true,
  "last": true,
  "numberOfElements": 4
}
  